LeIA/__init__.py
LeIA/leia.py
LeIA/lexicons/booster.txt
LeIA/lexicons/emoji_utf8_lexicon_ptbr.txt
LeIA/lexicons/negate.txt
LeIA/lexicons/vader_lexicon_ptbr.txt
leia_br-0.0.1.dist-info/LICENSE.txt
leia_br-0.0.1.dist-info/METADATA
leia_br-0.0.1.dist-info/WHEEL
leia_br-0.0.1.dist-info/top_level.txt
leia_br-0.0.1.dist-info/RECORD
