Metadata-Version: 2.1
Name: leia-br
Version: 0.0.1
Summary: LeIA (Léxico para Inferência Adaptada) é um fork do léxico e ferramenta para análise de sentimentos VADER (Valence Aware Dictionary and sEntiment Reasoner) adaptado para textos em português.
Home-page: https://github.com/wpcasarin/LeIA
Author: C.J. Hutto
Author-email: cjhutto@gatech.edu
License: MIT License: http://opensource.org/licenses/MIT
Keywords: vader,sentiment,analysis,opinion,mining,nlp,text,data,text analysis,opinion analysis,sentiment analysis,text mining,twitter sentiment,opinion mining,social media,twitter,social,media
Platform: any
Classifier: Development Status :: 4 - Beta
Classifier: Intended Audience :: Science/Research
Classifier: License :: OSI Approved :: MIT License
Classifier: Natural Language :: English
Classifier: Programming Language :: Python :: 3.5
Classifier: Topic :: Scientific/Engineering :: Artificial Intelligence
Classifier: Topic :: Scientific/Engineering :: Information Analysis
Classifier: Topic :: Text Processing :: Linguistic
Classifier: Topic :: Text Processing :: General
License-File: LICENSE.txt
